svg2unicode/README.md
svg2unicode/__init__.py
svg2unicode/cli.py
svg2unicode/converter.py
svg2unicode-0.1.5.dist-info/LICENSE
svg2unicode-0.1.5.dist-info/METADATA
svg2unicode-0.1.5.dist-info/WHEEL
svg2unicode-0.1.5.dist-info/entry_points.txt
svg2unicode-0.1.5.dist-info/RECORD
