Metadata-Version: 2.3
Name: svg2unicode
Version: 0.1.5
Summary: Convert SVG files to Unicode block characters for terminal display
License: MIT
Keywords: svg,unicode,terminal,graphics,conversion
Author: Tom Sapletta
Author-email: info@softreck.dev
Requires-Python: >=3.7
Classifier: Development Status :: 4 - Beta
Classifier: Environment :: Console
Classifier: Intended Audience :: Developers
Classifier: License :: OSI Approved :: MIT License
Classifier: Operating System :: OS Independent
Classifier: Programming Language :: Python :: 3
Classifier: Programming Language :: Python :: 3.7
Classifier: Programming Language :: Python :: 3.8
Classifier: Programming Language :: Python :: 3.9
Classifier: Programming Language :: Python :: 3.10
Classifier: Programming Language :: Python :: 3.11
Classifier: Programming Language :: Python :: 3.12
Classifier: Programming Language :: Python :: 3.13
Classifier: Topic :: Multimedia :: Graphics :: Graphics Conversion
Classifier: Topic :: Terminals
Classifier: Topic :: Utilities
Provides-Extra: dev
Requires-Dist: Pillow (>=9.0.0)
Requires-Dist: cairosvg (>=2.5.0)
Project-URL: Documentation, https://github.com/veridock/svg2unicode#readme
Project-URL: Homepage, https://github.com/veridock/svg2unicode
Project-URL: Repository, https://github.com/veridock/svg2unicode
